rtl/core/riscv_defines.svh
// ============================================================================
// riscv_defines.svh — shared constants for the RV32I core
// ----------------------------------------------------------------------------
// ALU operation encoding: {funct7[5], funct3}
// This is exactly how RV32I encodes register-register ALU ops in the
// instruction itself, so the decoder can mostly pass these bits through.
// ============================================================================

`ifndef RISCV_DEFINES_SVH
`define RISCV_DEFINES_SVH

// ---- ALU operations: {instr[30], funct3} -----------------------------------
`define ALU_ADD  4'b0000  // add
`define ALU_SUB  4'b1000  // subtract        (instr[30] set)
`define ALU_SLL  4'b0001  // shift left logical
`define ALU_SLT  4'b0010  // set if less than (signed)
`define ALU_SLTU 4'b0011  // set if less than (unsigned)
`define ALU_XOR  4'b0100  // exclusive or
`define ALU_SRL  4'b0101  // shift right logical
`define ALU_SRA  4'b1101  // shift right arithmetic (instr[30] set)
`define ALU_OR   4'b0110  // or
`define ALU_AND  4'b0111  // and

// ---- RV32I opcodes (instr[6:0]) ---------------------------------------------
`define OPC_LUI    7'b0110111  // load upper immediate
`define OPC_AUIPC  7'b0010111  // add upper immediate to PC
`define OPC_JAL    7'b1101111  // jump and link
`define OPC_JALR   7'b1100111  // jump and link register (function return)
`define OPC_BRANCH 7'b1100011  // BEQ / BNE / ...
`define OPC_LOAD   7'b0000011  // LW
`define OPC_STORE  7'b0100011  // SW
`define OPC_OPIMM  7'b0010011  // ALU with immediate (ADDI, ...)
`define OPC_OP     7'b0110011  // ALU register-register (ADD, ...)

// ---- Immediate format select (imm_gen) ----------------------------------------
`define IMM_I 3'b000  // I-type: ADDI, LW, JALR
`define IMM_S 3'b001  // S-type: SW
`define IMM_B 3'b010  // B-type: branches
`define IMM_U 3'b011  // U-type: LUI, AUIPC
`define IMM_J 3'b100  // J-type: JAL

// ---- ALU operand A select ------------------------------------------------------
`define OPA_RS1  2'b00  // normal ALU ops
`define OPA_PC   2'b01  // AUIPC
`define OPA_ZERO 2'b10  // LUI (0 + imm)

// ---- ALU operand B select ------------------------------------------------------
`define OPB_RS2 1'b0
`define OPB_IMM 1'b1

// ---- Write-back source select ---------------------------------------------------
`define WB_ALU 2'b00  // ALU result
`define WB_MEM 2'b01  // load data
`define WB_PC4 2'b10  // PC+4 (JAL/JALR link address)

// ---- Reset / boot address ---------------------------------------------------
`define RESET_PC 32'h0000_0000

`endif // RISCV_DEFINES_SVH

rtl/core/alu.sv
// ============================================================================
// alu.sv — Arithmetic Logic Unit (RV32I)
// ----------------------------------------------------------------------------
// Purpose:
//   Pure combinational block that computes one result from two 32-bit
//   operands. Supports the ten RV32I ALU operations:
//     ADD SUB AND OR XOR SLL SRL SRA SLT SLTU
//
// Operation encoding: op_i = {funct7[5], funct3}
//   This is the instruction's own encoding, so the decoder mostly passes
//   instruction bits straight through — minimal decode logic, and each op
//   code below can be read directly out of the RISC-V spec.
//
// Notes on the interesting cases:
//   - Shifts use only b_i[4:0]: shifting a 32-bit value by >31 is meaningless,
//     and the RV32I spec says exactly this (the shamt field is 5 bits).
//   - SRA needs $signed() so Verilog performs an arithmetic shift
//     (sign bit replicated) instead of filling with zeros.
//   - SLT compares as signed, SLTU as unsigned; both produce 0 or 1.
//   - zero_o flags result == 0. The branch unit uses it: BEQ does
//     SUB and branches if zero_o is set.
//
// Timing:
//   Fully combinational — no clock, no state. Result is valid after
//   propagation delay within the same cycle.
// ============================================================================

`include "riscv_defines.svh"

module alu (
    input  logic [31:0] a_i,       // operand A (rs1)
    input  logic [31:0] b_i,       // operand B (rs2 or immediate)
    input  logic [3:0]  op_i,      // {funct7[5], funct3}
    output logic [31:0] result_o,
    output logic        zero_o     // result_o == 0 (for branches)
);

  always_comb begin
    unique case (op_i)
      `ALU_ADD:  result_o = a_i + b_i;
      `ALU_SUB:  result_o = a_i - b_i;
      `ALU_AND:  result_o = a_i & b_i;
      `ALU_OR:   result_o = a_i | b_i;
      `ALU_XOR:  result_o = a_i ^ b_i;
      `ALU_SLL:  result_o = a_i << b_i[4:0];
      `ALU_SRL:  result_o = a_i >> b_i[4:0];
      `ALU_SRA:  result_o = $signed(a_i) >>> b_i[4:0];
      `ALU_SLT:  result_o = ($signed(a_i) < $signed(b_i)) ? 32'd1 : 32'd0;
      `ALU_SLTU: result_o = (a_i < b_i) ? 32'd1 : 32'd0;
      default:   result_o = 32'd0;  // unused encodings: defined output, no latch
    endcase
  end

  assign zero_o = (result_o == 32'd0);

endmodule

tb/unit/tb_alu.sv
// ============================================================================
// tb_alu.sv — self-checking testbench for the ALU
// ----------------------------------------------------------------------------
// Strategy:
//   1. Directed tests: known corner cases per operation (overflow wrap,
//      sign boundaries, shift by 0/31, shift amount masking, zero flag)
//   2. Random tests: 1000 random operand/op pairs checked against an
//      independent reference model
// ============================================================================

`timescale 1ns / 1ps
`include "riscv_defines.svh"

module tb_alu;

  logic [31:0] a, b, result;
  logic [3:0]  op;
  logic        zero;

  int errors = 0;
  int checks = 0;

  alu dut (
      .a_i     (a),
      .b_i     (b),
      .op_i    (op),
      .result_o(result),
      .zero_o  (zero)
  );

  // independent reference model
  function automatic [31:0] ref_model(input [31:0] x, input [31:0] y,
                                      input [3:0] f);
    case (f)
      `ALU_ADD:  ref_model = x + y;
      `ALU_SUB:  ref_model = x - y;
      `ALU_AND:  ref_model = x & y;
      `ALU_OR:   ref_model = x | y;
      `ALU_XOR:  ref_model = x ^ y;
      `ALU_SLL:  ref_model = x << y[4:0];
      `ALU_SRL:  ref_model = x >> y[4:0];
      `ALU_SRA:  ref_model = $signed(x) >>> y[4:0];
      `ALU_SLT:  ref_model = ($signed(x) < $signed(y)) ? 1 : 0;
      `ALU_SLTU: ref_model = (x < y) ? 1 : 0;
      default:   ref_model = 0;
    endcase
  endfunction

  task automatic test(input [31:0] x, input [31:0] y, input [3:0] f,
                      input [31:0] expected, input string what);
    a = x; b = y; op = f;
    #1;
    checks++;
    if (result !== expected) begin
      errors++;
      $display("FAIL: %s | a=0x%08h b=0x%08h op=%b | expected 0x%08h got 0x%08h",
               what, x, y, f, expected, result);
    end
    checks++;
    if (zero !== (expected == 0)) begin
      errors++;
      $display("FAIL: %s | zero flag wrong (result 0x%08h, zero=%b)",
               what, result, zero);
    end
  endtask

  logic [3:0] ops[0:9];
  logic [3:0] rop;
  logic [31:0] ra, rb;

  initial begin
    $dumpfile("tb_alu.vcd");
    $dumpvars(0, tb_alu);

    ops[0] = `ALU_ADD;  ops[1] = `ALU_SUB;  ops[2] = `ALU_AND;
    ops[3] = `ALU_OR;   ops[4] = `ALU_XOR;  ops[5] = `ALU_SLL;
    ops[6] = `ALU_SRL;  ops[7] = `ALU_SRA;  ops[8] = `ALU_SLT;
    ops[9] = `ALU_SLTU;

    // ---- ADD: basic, wraparound overflow ---------------------------------
    test(5, 10, `ALU_ADD, 15, "ADD 5+10");
    test(32'hFFFF_FFFF, 1, `ALU_ADD, 0, "ADD wrap to zero (zero flag)");
    test(32'h7FFF_FFFF, 1, `ALU_ADD, 32'h8000_0000, "ADD signed overflow wraps");

    // ---- SUB: basic, negative result, equality (branch use) ---------------
    test(10, 5, `ALU_SUB, 5, "SUB 10-5");
    test(5, 10, `ALU_SUB, -5, "SUB negative result");
    test(32'hCAFE_CAFE, 32'hCAFE_CAFE, `ALU_SUB, 0, "SUB equal -> zero flag (BEQ)");

    // ---- logic ops ---------------------------------------------------------
    test(32'hF0F0_F0F0, 32'h0FF0_0FF0, `ALU_AND, 32'h00F0_00F0, "AND");
    test(32'hF0F0_F0F0, 32'h0FF0_0FF0, `ALU_OR,  32'hFFF0_FFF0, "OR");
    test(32'hF0F0_F0F0, 32'h0FF0_0FF0, `ALU_XOR, 32'hFF00_FF00, "XOR");
    test(32'hAAAA_5555, 32'hAAAA_5555, `ALU_XOR, 0, "XOR self -> zero");

    // ---- shifts: 0, max, and shamt masking (bit 5+ ignored) ---------------
    test(32'h0000_0001, 0,  `ALU_SLL, 32'h0000_0001, "SLL by 0");
    test(32'h0000_0001, 31, `ALU_SLL, 32'h8000_0000, "SLL by 31");
    test(32'h0000_0001, 32'h0000_0020, `ALU_SLL, 32'h0000_0001,
         "SLL shamt masked to 5 bits (32 -> 0)");
    test(32'h8000_0000, 31, `ALU_SRL, 1, "SRL by 31 zero-fills");
    test(32'h8000_0000, 31, `ALU_SRA, 32'hFFFF_FFFF, "SRA by 31 sign-fills");
    test(32'h7FFF_FFFF, 4,  `ALU_SRA, 32'h07FF_FFFF, "SRA positive zero-fills");

    // ---- comparisons: sign boundary cases ----------------------------------
    test(-1, 1, `ALU_SLT, 1, "SLT -1 < 1 (signed)");
    test(-1, 1, `ALU_SLTU, 0, "SLTU 0xFFFFFFFF > 1 (unsigned)");
    test(1, -1, `ALU_SLT, 0, "SLT 1 < -1 false");
    test(32'h8000_0000, 32'h7FFF_FFFF, `ALU_SLT, 1, "SLT INT_MIN < INT_MAX");
    test(5, 5, `ALU_SLT, 0, "SLT equal -> 0 (zero flag)");

    // ---- random soak vs reference model ------------------------------------
    for (int n = 0; n < 1000; n++) begin
      ra  = $random;
      rb  = $random;
      rop = ops[{$random} % 10];
      test(ra, rb, rop, ref_model(ra, rb, rop), "random");
    end

    // ---- Summary -------------------------------------------------------------
    if (errors == 0) $display("RESULT: PASS (%0d checks)", checks);
    else             $display("RESULT: FAIL (%0d/%0d checks failed)", errors, checks);
    $finish;
  end

endmodule

sim/icarus/build/tb_alu.vcd
$date
	Sun Jul  5 00:54:39 2026
$end
$version
	Icarus Verilog
$end
$timescale
	1ps
$end
$scope module tb_alu $end
$var wire 1 ! zero $end
$var wire 32 " result [31:0] $end
$var reg 32 # a [31:0] $end
$var reg 32 $ b [31:0] $end
$var reg 4 % op [3:0] $end
$var reg 32 & ra [31:0] $end
$var reg 32 ' rb [31:0] $end
$var reg 4 ( rop [3:0] $end
$var integer 32 ) checks [31:0] $end
$var integer 32 * errors [31:0] $end
$scope function ref_model $end
$upscope $end
$scope module dut $end
$var wire 32 + a_i [31:0] $end
$var wire 32 , b_i [31:0] $end
$var wire 4 - op_i [3:0] $end
$var wire 1 ! zero_o $end
$var reg 32 . result_o [31:0] $end
$upscope $end
$scope begin $ivl_for_loop0 $end
$var integer 32 / n [31:0] $end
$upscope $end
$scope task test $end
$upscope $end
$upscope $end
$enddefinitions $end
#0
$dumpvars
b0 /
b1111 .
b0 -
b1010 ,
b101 +
b0 *
b0 )
bx (
bx '
bx &
b0 %
b1010 $
b101 #
b1111 "
0!
$end
#1000
1!
b0 "
b0 .
b1 $
b1 ,
b11111111111111111111111111111111 #
b11111111111111111111111111111111 +
b10 )
#2000
0!
b10000000000000000000000000000000 "
b10000000000000000000000000000000 .
b1111111111111111111111111111111 #
b1111111111111111111111111111111 +
b100 )
#3000
b101 "
b101 .
b1000 %
b1000 -
b101 $
b101 ,
b1010 #
b1010 +
b110 )
#4000
b11111111111111111111111111111011 "
b11111111111111111111111111111011 .
b1010 $
b1010 ,
b101 #
b101 +
b1000 )
#5000
1!
b0 "
b0 .
b11001010111111101100101011111110 $
b11001010111111101100101011111110 ,
b11001010111111101100101011111110 #
b11001010111111101100101011111110 +
b1010 )
#6000
0!
b111100000000000011110000 "
b111100000000000011110000 .
b111 %
b111 -
b1111111100000000111111110000 $
b1111111100000000111111110000 ,
b11110000111100001111000011110000 #
b11110000111100001111000011110000 +
b1100 )
#7000
b11111111111100001111111111110000 "
b11111111111100001111111111110000 .
b110 %
b110 -
b1110 )
#8000
b11111111000000001111111100000000 "
b11111111000000001111111100000000 .
b100 %
b100 -
b10000 )
#9000
1!
b0 "
b0 .
b10101010101010100101010101010101 $
b10101010101010100101010101010101 ,
b10101010101010100101010101010101 #
b10101010101010100101010101010101 +
b10010 )
#10000
0!
b1 "
b1 .
b1 %
b1 -
b0 $
b0 ,
b1 #
b1 +
b10100 )
#11000
b10000000000000000000000000000000 "
b10000000000000000000000000000000 .
b11111 $
b11111 ,
b10110 )
#12000
b1 "
b1 .
b100000 $
b100000 ,
b11000 )
#13000
b101 %
b101 -
b11111 $
b11111 ,
b10000000000000000000000000000000 #
b10000000000000000000000000000000 +
b11010 )
#14000
b11111111111111111111111111111111 "
b11111111111111111111111111111111 .
b1101 %
b1101 -
b11100 )
#15000
b111111111111111111111111111 "
b111111111111111111111111111 .
b100 $
b100 ,
b1111111111111111111111111111111 #
b1111111111111111111111111111111 +
b11110 )
#16000
b1 "
b1 .
b10 %
b10 -
b1 $
b1 ,
b11111111111111111111111111111111 #
b11111111111111111111111111111111 +
b100000 )
#17000
1!
b0 "
b0 .
b11 %
b11 -
b100010 )
#18000
b10 %
b10 -
b11111111111111111111111111111111 $
b11111111111111111111111111111111 ,
b1 #
b1 +
b100100 )
#19000
0!
b1 "
b1 .
b1111111111111111111111111111111 $
b1111111111111111111111111111111 ,
b10000000000000000000000000000000 #
b10000000000000000000000000000000 +
b100110 )
#20000
1!
b0 "
b0 .
b101 $
b101 ,
b101 #
b101 +
b101000 )
#21000
0!
b1001000010101001101010010010 "
b1001000010101001101010010010 .
b1101 %
b1101 -
b11000000100010010101111010000001 $
b11000000100010010101111010000001 ,
b10010000101010011010100100100 #
b10010000101010011010100100100 +
b1101 (
b11000000100010010101111010000001 '
b10010000101010011010100100100 &
b101010 )
#22000
b11111111111111011000111110000010 "
b11111111111111011000111110000010 .
b110101110010111101100001101 $
b110101110010111101100001101 ,
b10110001111100000101011001100011 #
b10110001111100000101011001100011 +
b110101110010111101100001101 '
b10110001111100000101011001100011 &
b1 /
b101100 )
#23000
b101001100010110011001001010011 "
b101001100010110011001001010011 .
b1000 %
b1000 -
b10001001001101110101001000010010 $
b10001001001101110101001000010010 ,
b10110010110000101000010001100101 #
b10110010110000101000010001100101 +
b1000 (
b10001001001101110101001000010010 '
b10110010110000101000010001100101 &
b10 /
b101110 )
#24000
b11011 "
b11011 .
b1101 %
b1101 -
b111011001000111111000101110110 $
b111011001000111111000101110110 ,
b110110101111100110100001101 #
b110110101111100110100001101 +
b1101 (
b111011001000111111000101110110 '
b110110101111100110100001101 &
b11 /
b110000 )
#25000
1!
b0 "
b0 .
b11 %
b11 -
b1000110001011011111011110001100 $
b1000110001011011111011110001100 ,
b1110110110101000101011111101101 #
b1110110110101000101011111101101 +
b11 (
b1000110001011011111011110001100 '
b1110110110101000101011111101101 &
b100 /
b110010 )
#26000
0!
b11100010001101110000010011000100 "
b11100010001101110000010011000100 .
b111 %
b111 -
b11100010111101111000010011000101 $
b11100010111101111000010011000101 ,
b11100011001101110010010011000110 #
b11100011001101110010010011000110 +
b111 (
b11100010111101111000010011000101 '
b11100011001101110010010011000110 &
b101 /
b110100 )
#27000
b11001001011111011000010110010010 "
b11001001011111011000010110010010 .
b100 %
b100 -
b10111011110100100111001001110111 $
b10111011110100100111001001110111 ,
b1110010101011111111011111100101 #
b1110010101011111111011111100101 +
b100 (
b10111011110100100111001001110111 '
b1110010101011111111011111100101 &
b110 /
b110110 )
#28000
b11000001000111010100010110000001 "
b11000001000111010100010110000001 .
b0 %
b0 -
b1111001001100000110100111110010 $
b1111001001100000110100111110010 ,
b1000111111011001101101110001111 #
b1000111111011001101101110001111 +
b0 (
b1111001001100000110100111110010 '
b1000111111011001101101110001111 &
b111 /
b111000 )
#29000
b10110110010100011010000101101 "
b10110110010100011010000101101 .
b100 %
b100 -
b11100010110010100100111011000101 $
b11100010110010100100111011000101 ,
b11110100000000000111101011101000 #
b11110100000000000111101011101000 +
b100 (
b11100010110010100100111011000101 '
b11110100000000000111101011101000 &
b1000 /
b111010 )
#30000
1!
b0 "
b0 .
b11 %
b11 -
b10010110101010110101100000101101 $
b10010110101010110101100000101101 ,
b11011110100011100010100010111101 #
b11011110100011100010100010111101 +
b11 (
b10010110101010110101100000101101 '
b11011110100011100010100010111101 &
b1001 /
b111100 )
#31000
0!
b1 "
b1 .
b10 %
b10 -
b101011100111000011100001010 $
b101011100111000011100001010 ,
b10110001111011110110001001100011 #
b10110001111011110110001001100011 +
b10 (
b101011100111000011100001010 '
b10110001111011110110001001100011 &
b1010 /
b111110 )
#32000
b10111010111010111101101101110110 "
b10111010111010111101101101110110 .
b1000 %
b1000 -
b1010101011110000100010110101010 $
b1010101011110000100010110101010 ,
b10000011001000010000100100000 #
b10000011001000010000100100000 +
b1000 (
b1010101011110000100010110101010 '
b10000011001000010000100100000 &
b1011 /
b1000000 )
#33000
b1000001100111001000011010000011 "
b1000001100111001000011010000011 .
b10001001100000111011100000010011 $
b10001001100000111011100000010011 ,
b11001011001000000011111010010110 #
b11001011001000000011111010010110 +
b10001001100000111011100000010011 '
b11001011001000000011111010010110 &
b1100 /
b1000010 )
#34000
b111110101100101001100000000000 "
b111110101100101001100000000000 .
b1 %
b1 -
b110101100111111101110101101011 $
b110101100111111101110101101011 ,
b10101001101001111101011001010011 #
b10101001101001111101011001010011 +
b1 (
b110101100111111101110101101011 '
b10101001101001111101011001010011 &
b1101 /
b1000100 )
#35000
b10101001110000010000101101010100 "
b10101001110000010000101101010100 .
b1000 %
b1000 -
b11010111010101100011111010101110 $
b11010111010101100011111010101110 ,
b10000001000101110100101000000010 #
b10000001000101110100101000000010 +
b1000 (
b11010111010101100011111010101110 '
b10000001000101110100101000000010 &
b1110 /
b1000110 )
#36000
b11111001010010011011101111110010 "
b11111001010010011011101111110010 .
b0 %
b0 -
b10001100001000100100100100011 $
b10001100001000100100100100011 ,
b11100111110001010111001011001111 #
b11100111110001010111001011001111 +
b0 (
b10001100001000100100100100011 '
b11100111110001010111001011001111 &
b1111 /
b1001000 )
#37000
b1110 "
b1110 .
b101 %
b101 -
b10011110001100010100110000111100 $
b10011110001100010100110000111100 ,
b11100101011100110000101011001010 #
b11100101011100110000101011001010 +
b101 (
b10011110001100010100110000111100 '
b11100101011100110000101011001010 &
b10000 /
b1001010 )
#38000
b1100101111010101101001011001011 "
b1100101111010101101001011001011 .
b100 %
b100 -
b100000110001001011001101000001 $
b100000110001001011001101000001 ,
b1000101001011100110000110001010 #
b1000101001011100110000110001010 +
b100 (
b100000110001001011001101000001 '
b1000101001011100110000110001010 &
b10001 /
b1001100 )
#39000
b111100001000001111001 "
b111100001000001111001 .
b1101 %
b1101 -
b11000100100010100001001010001001 $
b11000100100010100001001010001001 ,
b111100001000001111001101111000 #
b111100001000001111001101111000 +
b1101 (
b11000100100010100001001010001001 '
b111100001000001111001101111000 &
b10010 /
b1001110 )
#40000
b1011011000000100110010110 "
b1011011000000100110010110 .
b101 %
b101 -
b1100011010010111111100111000110 $
b1100011010010111111100111000110 ,
b1011011000000100110010110110110 #
b1011011000000100110010110110110 +
b101 (
b1100011010010111111100111000110 '
b1011011000000100110010110110110 &
b10011 /
b1010000 )
#41000
b11011111011111111101111110111110 "
b11011111011111111101111110111110 .
b110 %
b110 -
b10101000011111101110100101010 $
b10101000011111101110100101010 ,
b11011110011101010000001010111100 #
b11011110011101010000001010111100 +
b110 (
b10101000011111101110100101010 '
b11011110011101010000001010111100 &
b10100 /
b1010010 )
#42000
b10010111101111100111000100000 "
b10010111101111100111000100000 .
b1 %
b1 -
b1000010111100100100000110000101 $
b1000010111100100100000110000101 ,
b10111000100101111011111001110001 #
b10111000100101111011111001110001 +
b1 (
b1000010111100100100000110000101 '
b10111000100101111011111001110001 &
b10101 /
b1010100 )
#43000
b11101000001000010000000111010 "
b11101000001000010000000111010 .
b111 %
b111 -
b11101000001100011001100111010 $
b11101000001100011001100111010 ,
b10011101110011000110000000111011 #
b10011101110011000110000000111011 +
b111 (
b11101000001100011001100111010 '
b10011101110011000110000000111011 &
b10110 /
b1010110 )
#44000
b10010001110100001010111100100100 "
b10010001110100001010111100100100 .
b1000 %
b1000 -
b1111000110110011001101111110001 $
b1111000110110011001101111110001 ,
b1010101010100100101100010101 #
b1010101010100100101100010101 +
b1000 (
b1111000110110011001101111110001 '
b1010101010100100101100010101 &
b10111 /
b1011000 )
#45000
1!
b0 "
b0 .
b11 %
b11 -
b100110001101011111101101001100 $
b100110001101011111101101001100 ,
b110001001000110000011101100010 #
b110001001000110000011101100010 +
b11 (
b100110001101011111101101001100 '
b110001001000110000011101100010 &
b11000 /
b1011010 )
#46000
0!
b1111111111111011010100111111111 "
b1111111111111011010100111111111 .
b110 %
b110 -
b1111100011011011010100111111000 $
b1111100011011011010100111111000 ,
b1000111101110011010000110001111 #
b1000111101110011010000110001111 +
b110 (
b1111100011011011010100111111000 '
b1000111101110011010000110001111 &
b11001 /
b1011100 )
#47000
1!
b0 "
b0 .
b11 %
b11 -
b10101110011111011001010001011100 $
b10101110011111011001010001011100 ,
b11001111110001000101011010011111 #
b11001111110001000101011010011111 +
b11 (
b10101110011111011001010001011100 '
b11001111110001000101011010011111 &
b11010 /
b1011110 )
#48000
0!
b100100011100011001000001001 "
b100100011100011001000001001 .
b111 %
b111 -
b10100100101011100011001001001001 $
b10100100101011100011001001001001 ,
b1000100110111100011011110001001 #
b1000100110111100011011110001001 +
b111 (
b10100100101011100011001001001001 '
b1000100110111100011011110001001 &
b11011 /
b1100000 )
#49000
b10010100110001101011110100101000 "
b10010100110001101011110100101000 .
b0 %
b0 -
b10101000110001111111110001010001 $
b10101000110001111111110001010001 ,
b11101011111111101100000011010111 #
b11101011111111101100000011010111 +
b0 (
b10101000110001111111110001010001 '
b11101011111111101100000011010111 &
b11100 /
b1100010 )
#50000
b11100111001100011011000111001110 "
b11100111001100011011000111001110 .
b100 %
b100 -
b11100001001011001100111011000010 $
b11100001001011001100111011000010 ,
b110000111010111111100001100 #
b110000111010111111100001100 +
b100 (
b11100001001011001100111011000010 '
b110000111010111111100001100 &
b11101 /
b1100100 )
#51000
b1 "
b1 .
b10 %
b10 -
b11110111100101110110100111101 $
b11110111100101110110100111101 ,
b10111011100000100101101001110111 #
b10111011100000100101101001110111 +
b10 (
b11110111100101110110100111101 '
b10111011100000100101101001110111 &
b11110 /
b1100110 )
#52000
b10111111111001011000000101111111 "
b10111111111001011000000101111111 .
b110 %
b110 -
b110110111001011000000101101101 $
b110110111001011000000101101101 ,
b10111111000001010000000001111110 #
b10111111000001010000000001111110 +
b110 (
b110110111001011000000101101101 '
b10111111000001010000000001111110 &
b11111 /
b1101000 )
#53000
b11101111111110111111111111011111 "
b11101111111110111111111111011111 .
b11101001111010111111011011010011 $
b11101001111010111111011011010011 ,
b1111110100101000111100011111 #
b1111110100101000111100011111 +
b11101001111010111111011011010011 '
b1111110100101000111100011111 &
b100000 /
b1101010 )
#54000
b10111101110111101101100101111011 "
b10111101110111101101100101111011 .
b101101110110100101100101011011 $
b101101110110100101100101011011 ,
b10111100000101001000100001111000 #
b10111100000101001000100001111000 +
b101101110110100101100101011011 '
b10111100000101001000100001111000 &
b100001 /
b1101100 )
#55000
b10101000000001010111000101010 "
b10101000000001010111000101010 .
b111 %
b111 -
b10101000011001010111100101010 $
b10101000011001010111100101010 ,
b10011111111100101010111000111111 #
b10011111111100101010111000111111 +
b111 (
b10101000011001010111100101010 '
b10011111111100101010111000111111 &
b100010 /
b1101110 )
#56000
b110000110011111100 "
b110000110011111100 .
b101 %
b101 -
b11000111000110100000110010001110 $
b11000111000110100000110010001110 ,
b11000011001111110011100010000110 #
b11000011001111110011100010000110 +
b101 (
b11000111000110100000110010001110 '
b11000011001111110011100010000110 &
b100011 /
b1110000 )
#57000
b1001101011001100111111010000000 "
b1001101011001100111111010000000 .
b1 %
b1 -
b10010011011111011011110000100110 $
b10010011011111011011110000100110 ,
b1111101001101011001100111111010 #
b1111101001101011001100111111010 +
b1 (
b10010011011111011011110000100110 '
b1111101001101011001100111111010 &
b100100 /
b1110010 )
#58000
b11111111111111111010001100010111 "
b11111111111111111010001100010111 .
b1101 %
b1101 -
b10010111100110011010100000101111 $
b10010111100110011010100000101111 ,
b11010001100010111011010010100011 #
b11010001100010111011010010100011 +
b1101 (
b10010111100110011010100000101111 '
b11010001100010111011010010100011 &
b100101 /
b1110100 )
#59000
b10001101101011110100100100011011 "
b10001101101011110100100100011011 .
b1000 %
b1000 -
b100010001010010000110101000100 $
b100010001010010000110101000100 ,
b10101111110110000101011001011111 #
b10101111110110000101011001011111 +
b1000 (
b100010001010010000110101000100 '
b10101111110110000101011001011111 &
b100110 /
b1110110 )
#60000
b10110100100100010110000101101 "
b10110100100100010110000101101 .
b100 %
b100 -
b11110011000010010001101011100110 $
b11110011000010010001101011100110 ,
b11100101100110110011011011001011 #
b11100101100110110011011011001011 +
b100 (
b11110011000010010001101011100110 '
b11100101100110110011011011001011 &
b100111 /
b1111000 )
#61000
b1010011001111110 "
b1010011001111110 .
b101 %
b101 -
b11110110100000101110001011101101 $
b11110110100000101110001011101101 ,
b10100110011111100000100101001 #
b10100110011111100000100101001 +
b101 (
b11110110100000101110001011101101 '
b10100110011111100000100101001 &
b101000 /
b1111010 )
#62000
b11001100101000000000000000000000 "
b11001100101000000000000000000000 .
b1 %
b1 -
b11011010100010101110001010110101 $
b11011010100010101110001010110101 ,
b10110010100111111011011001100101 #
b10110010100111111011011001100101 +
b1 (
b11011010100010101110001010110101 '
b10110010100111111011011001100101 &
b101001 /
b1111100 )
#63000
1!
b0 "
b0 .
b10 %
b10 -
b100010001100011111111101000100 $
b100010001100011111111101000100 ,
b111100111100010001100101111001 #
b111100111100010001100101111001 +
b10 (
b100010001100011111111101000100 '
b111100111100010001100101111001 &
b101010 /
b1111110 )
#64000
0!
b1000000111111111010011010000001 "
b1000000111111111010011010000001 .
b100 %
b100 -
b1010101111101101010110110101011 $
b1010101111101101010110110101011 ,
b10101000010010000101100101010 #
b10101000010010000101100101010 +
b100 (
b1010101111101101010110110101011 '
b10101000010010000101100101010 &
b101011 /
b10000000 )
#65000
b1 "
b1 .
b11 %
b11 -
b11001101010111101011110010011010 $
b11001101010111101011110010011010 ,
b1101110010111011010110111011100 #
b1101110010111011010110111011100 +
b11 (
b11001101010111101011110010011010 '
b1101110010111011010110111011100 &
b101100 /
b10000010 )
#66000
b1110000111 "
b1110000111 .
b101 %
b101 -
b101011000011101110110101010110 $
b101011000011101110110101010110 ,
b11100001111100010000001011000011 #
b11100001111100010000001011000011 +
b101 (
b101011000011101110110101010110 '
b11100001111100010000001011000011 &
b101101 /
b10000100 )
#67000
b110110111010000100001001101101 "
b110110111010000100001001101101 .
b100 %
b100 -
b10000101001100010011010000001010 $
b10000101001100010011010000001010 ,
b10110011110110010111011001100111 #
b10110011110110010111011001100111 +
b100 (
b10000101001100010011010000001010 '
b10110011110110010111011001100111 &
b101110 /
b10000110 )
#68000
b1 "
b1 .
b10 %
b10 -
b111100110100011000011101111001 $
b111100110100011000011101111001 ,
b10011100000011101000101000111000 #
b10011100000011101000101000111000 +
b10 (
b111100110100011000011101111001 '
b10011100000011101000101000111000 &
b101111 /
b10001000 )
#69000
b100101001110 "
b100101001110 .
b101 %
b101 -
b1001001110001100101110110010011 $
b1001001110001100101110110010011 ,
b1001010011101001011111110010100 #
b1001010011101001011111110010100 +
b101 (
b1001001110001100101110110010011 '
b1001010011101001011111110010100 &
b110000 /
b10001010 )
#70000
b11111111111111111111111111110101 "
b11111111111111111111111111110101 .
b1101 %
b1101 -
b1101101110010110110100111011011 $
b1101101110010110110100111011011 ,
b10101100101101111100101001011001 #
b10101100101101111100101001011001 +
b1101 (
b1101101110010110110100111011011 '
b10101100101101111100101001011001 &
b110001 /
b10001100 )
#71000
b100011010101001101111001000110 "
b100011010101001101111001000110 .
b0 %
b0 -
b10110110101001000010011001101101 $
b10110110101001000010011001101101 ,
b1101100101100001011011111011001 #
b1101100101100001011011111011001 +
b0 (
b10110110101001000010011001101101 '
b1101100101100001011011111011001 &
b110010 /
b10001110 )
#72000
b1111111001111110110110111111110 "
b1111111001111110110110111111110 .
b110 %
b110 -
b1011011000101110010110110110110 $
b1011011000101110010110110110110 ,
b1100101001110110100100111001010 #
b1100101001110110100100111001010 +
b110 (
b1011011000101110010110110110110 '
b1100101001110110100100111001010 &
b110011 /
b10010000 )
#73000
b11111010001100000111000110100100 "
b11111010001100000111000110100100 .
b1101 %
b1101 -
b10011101001001101100000100 $
b10011101001001101100000100 ,
b10100011000001110001101001000110 #
b10100011000001110001101001000110 +
b1101 (
b10011101001001101100000100 '
b10100011000001110001101001000110 &
b110100 /
b10010010 )
#74000
b1101001001 "
b1101001001 .
b101 %
b101 -
b11011010011011101011101010110100 $
b11011010011011101011101010110100 ,
b110100100110000000011101101001 #
b110100100110000000011101101001 +
b101 (
b11011010011011101011101010110100 '
b110100100110000000011101101001 &
b110101 /
b10010100 )
#75000
b1111101111011001101010011111011 "
b1111101111011001101010011111011 .
b1000 %
b1000 -
b10010110100100000000010000101101 $
b10010110100100000000010000101101 ,
b10100011111001101100100101000 #
b10100011111001101100100101000 +
b1000 (
b10010110100100000000010000101101 '
b10100011111001101100100101000 &
b110110 /
b10010110 )
#76000
b100101110101110010011100 "
b100101110101110010011100 .
b101 %
b101 -
b10000100011101111110010000001000 $
b10000100011101111110010000001000 ,
b10010111010111001001110000101110 #
b10010111010111001001110000101110 +
b101 (
b10000100011101111110010000001000 '
b10010111010111001001110000101110 &
b110111 /
b10011000 )
#77000
b11101010001110011010000111010100 "
b11101010001110011010000111010100 .
b100 %
b100 -
b10100100111100000011100101001 $
b10100100111100000011100101001 ,
b11111110101001111010011011111101 #
b11111110101001111010011011111101 +
b100 (
b10100100111100000011100101001 '
b11111110101001111010011011111101 &
b111000 /
b10011010 )
#78000
b11000000000000000000000000000 "
b11000000000000000000000000000 .
b1 %
b1 -
b11101101001101000000100011011010 $
b11101101001101000000100011011010 ,
b1000011001101010110011110000110 #
b1000011001101010110011110000110 +
b1 (
b11101101001101000000100011011010 '
b1000011001101010110011110000110 &
b111001 /
b10011100 )
