rtl/core/riscv_defines.svh
// ============================================================================
// riscv_defines.svh — shared constants for the RV32I core
// ----------------------------------------------------------------------------
// ALU operation encoding: {funct7[5], funct3}
// This is exactly how RV32I encodes register-register ALU ops in the
// instruction itself, so the decoder can mostly pass these bits through.
// ============================================================================

`ifndef RISCV_DEFINES_SVH
`define RISCV_DEFINES_SVH

// ---- ALU operations: {instr[30], funct3} -----------------------------------
`define ALU_ADD  4'b0000  // add
`define ALU_SUB  4'b1000  // subtract        (instr[30] set)
`define ALU_SLL  4'b0001  // shift left logical
`define ALU_SLT  4'b0010  // set if less than (signed)
`define ALU_SLTU 4'b0011  // set if less than (unsigned)
`define ALU_XOR  4'b0100  // exclusive or
`define ALU_SRL  4'b0101  // shift right logical
`define ALU_SRA  4'b1101  // shift right arithmetic (instr[30] set)
`define ALU_OR   4'b0110  // or
`define ALU_AND  4'b0111  // and

// ---- RV32I opcodes (instr[6:0]) ---------------------------------------------
`define OPC_LUI    7'b0110111  // load upper immediate
`define OPC_AUIPC  7'b0010111  // add upper immediate to PC
`define OPC_JAL    7'b1101111  // jump and link
`define OPC_JALR   7'b1100111  // jump and link register (function return)
`define OPC_BRANCH 7'b1100011  // BEQ / BNE / ...
`define OPC_LOAD   7'b0000011  // LW
`define OPC_STORE  7'b0100011  // SW
`define OPC_OPIMM  7'b0010011  // ALU with immediate (ADDI, ...)
`define OPC_OP     7'b0110011  // ALU register-register (ADD, ...)

// ---- Immediate format select (imm_gen) ----------------------------------------
`define IMM_I 3'b000  // I-type: ADDI, LW, JALR
`define IMM_S 3'b001  // S-type: SW
`define IMM_B 3'b010  // B-type: branches
`define IMM_U 3'b011  // U-type: LUI, AUIPC
`define IMM_J 3'b100  // J-type: JAL

// ---- ALU operand A select ------------------------------------------------------
`define OPA_RS1  2'b00  // normal ALU ops
`define OPA_PC   2'b01  // AUIPC
`define OPA_ZERO 2'b10  // LUI (0 + imm)

// ---- ALU operand B select ------------------------------------------------------
`define OPB_RS2 1'b0
`define OPB_IMM 1'b1

// ---- Write-back source select ---------------------------------------------------
`define WB_ALU 2'b00  // ALU result
`define WB_MEM 2'b01  // load data
`define WB_PC4 2'b10  // PC+4 (JAL/JALR link address)

// ---- Reset / boot address ---------------------------------------------------
`define RESET_PC 32'h0000_0000

`endif // RISCV_DEFINES_SVH

rtl/core/pc.sv
// ============================================================================
// pc.sv — Program Counter
// ----------------------------------------------------------------------------
// Purpose:
//   Holds the address of the instruction currently being fetched.
//   On every clock edge (when enabled) it loads the next address, which the
//   surrounding next-PC logic computes as either PC+4 (sequential execution)
//   or a branch/jump target. Keeping the "what is next?" decision OUTSIDE
//   this module keeps it tiny and reusable.
//
// Interface:
//   clk_i      : clock, all state changes on rising edge
//   rst_ni     : asynchronous reset, active LOW (industry convention).
//                On reset the PC becomes RESET_PC (0x0000_0000).
//   en_i       : update enable. 1 = load pc_next_i on next edge,
//                0 = hold current value (future use: stalls). Tie to 1 for now.
//   pc_next_i  : the address to load next (PC+4, branch or jump target)
//   pc_o       : current program counter value
//
// Timing:
//   pc_o changes only on the rising clock edge (or async on reset).
//   There is no combinational path from pc_next_i to pc_o.
// ============================================================================

`include "riscv_defines.svh"

module pc (
    input  logic        clk_i,
    input  logic        rst_ni,
    input  logic        en_i,
    input  logic [31:0] pc_next_i,
    output logic [31:0] pc_o
);

  always_ff @(posedge clk_i or negedge rst_ni) begin
    if (!rst_ni) begin
      pc_o <= `RESET_PC;
    end else if (en_i) begin
      pc_o <= pc_next_i;
    end
  end

endmodule

tb/unit/tb_pc.sv
// ============================================================================
// tb_pc.sv — self-checking testbench for the Program Counter
// ----------------------------------------------------------------------------
// Tests:
//   1. Reset drives pc_o to RESET_PC
//   2. Sequential increment (pc_next = pc + 4) works cycle by cycle
//   3. Branch/jump target loading works
//   4. en_i = 0 holds the current value (stall behavior)
//   5. Mid-run reset returns to RESET_PC
// Result: prints PASS/FAIL summary, non-zero error count = FAIL.
// ============================================================================

`timescale 1ns / 1ps
`include "riscv_defines.svh"

module tb_pc;

  logic        clk;
  logic        rst_n;
  logic        en;
  logic [31:0] pc_next;
  logic [31:0] pc_out;

  int errors = 0;
  int checks = 0;

  // Device under test
  pc dut (
      .clk_i    (clk),
      .rst_ni   (rst_n),
      .en_i     (en),
      .pc_next_i(pc_next),
      .pc_o     (pc_out)
  );

  // 100 MHz clock
  initial clk = 0;
  always #5 clk = ~clk;

  // Check helper: compare pc_out against expected value
  task automatic check(input [31:0] expected, input string what);
    checks++;
    if (pc_out !== expected) begin
      errors++;
      $display("FAIL: %s | expected 0x%08h, got 0x%08h (t=%0t)",
               what, expected, pc_out, $time);
    end
  endtask

  initial begin
    $dumpfile("tb_pc.vcd");
    $dumpvars(0, tb_pc);

    // ---- Test 1: reset value -------------------------------------------
    en      = 1;
    pc_next = 32'hDEAD_BEEF;  // must be ignored during reset
    rst_n   = 0;
    repeat (2) @(posedge clk);
    #1 check(`RESET_PC, "reset value");
    rst_n = 1;

    // ---- Test 2: sequential increments ---------------------------------
    for (int i = 0; i < 5; i++) begin
      pc_next = pc_out + 4;
      @(posedge clk);
      #1 check(32'h4 * (i + 1), "sequential PC+4");
    end

    // ---- Test 3: branch target load ------------------------------------
    pc_next = 32'h0000_0100;
    @(posedge clk);
    #1 check(32'h0000_0100, "branch target");

    // ---- Test 4: stall (en=0 holds value) -------------------------------
    en      = 0;
    pc_next = 32'hFFFF_FFF0;
    repeat (3) @(posedge clk);
    #1 check(32'h0000_0100, "hold while en=0");
    en = 1;

    // ---- Test 5: mid-run reset ------------------------------------------
    @(posedge clk);
    rst_n = 0;
    #1 check(`RESET_PC, "async mid-run reset");
    rst_n = 1;

    // ---- Summary ---------------------------------------------------------
    if (errors == 0) $display("RESULT: PASS (%0d checks)", checks);
    else             $display("RESULT: FAIL (%0d/%0d checks failed)", errors, checks);
    $finish;
  end

endmodule

sim/icarus/build/tb_pc.vcd
$date
	Wed Jul  8 00:00:47 2026
$end
$version
	Icarus Verilog
$end
$timescale
	1ps
$end
$scope module tb_pc $end
$var wire 32 ! pc_out [31:0] $end
$var reg 1 " clk $end
$var reg 1 # en $end
$var reg 32 $ pc_next [31:0] $end
$var reg 1 % rst_n $end
$var integer 32 & checks [31:0] $end
$var integer 32 ' errors [31:0] $end
$scope module dut $end
$var wire 1 " clk_i $end
$var wire 1 # en_i $end
$var wire 32 ( pc_next_i [31:0] $end
$var wire 1 % rst_ni $end
$var reg 32 ) pc_o [31:0] $end
$upscope $end
$scope begin $ivl_for_loop0 $end
$var integer 32 * i [31:0] $end
$upscope $end
$scope task check $end
$upscope $end
$upscope $end
$enddefinitions $end
#0
$dumpvars
b0 *
b0 )
b11011110101011011011111011101111 (
b0 '
b0 &
0%
b11011110101011011011111011101111 $
1#
0"
b0 !
$end
#5000
1"
#10000
0"
#15000
1"
#16000
b100 $
b100 (
1%
b1 &
#20000
0"
#25000
b100 !
b100 )
1"
#26000
b1000 $
b1000 (
b1 *
b10 &
#30000
0"
#35000
b1000 !
b1000 )
1"
#36000
b1100 $
b1100 (
b10 *
b11 &
#40000
0"
#45000
b1100 !
b1100 )
1"
#46000
b10000 $
b10000 (
b11 *
b100 &
#50000
0"
#55000
b10000 !
b10000 )
1"
#56000
b10100 $
b10100 (
b100 *
b101 &
#60000
0"
#65000
b10100 !
b10100 )
1"
#66000
b100000000 $
b100000000 (
b101 *
b110 &
#70000
0"
#75000
b100000000 !
b100000000 )
1"
#76000
b11111111111111111111111111110000 $
b11111111111111111111111111110000 (
0#
b111 &
#80000
0"
#85000
1"
#90000
0"
#95000
1"
#100000
0"
#105000
1"
#106000
1#
b1000 &
#110000
0"
#115000
b0 !
b0 )
0%
1"
#116000
1%
b1001 &
