rtl/core/regfile.sv
// ============================================================================
// regfile.sv — RV32I Register File
// ----------------------------------------------------------------------------
// Purpose:
//   32 general-purpose registers (x0..x31), each 32 bits wide.
//   RISC-V instructions read up to two registers (rs1, rs2) and write one
//   (rd) per instruction, hence: two read ports, one write port.
//
// The x0 rule:
//   Register x0 is hard-wired to zero in RISC-V. Writes to x0 are silently
//   discarded and reads always return 0. Software relies on this constantly
//   (e.g. "mv a0, a1" is really "addi a0, a1, 0"; comparisons against zero
//   use x0), so this behavior is enforced in hardware here, not left to
//   software convention.
//
// Interface:
//   clk_i     : clock, writes happen on rising edge
//   we_i      : write enable
//   waddr_i   : destination register index (rd)
//   wdata_i   : data to write
//   raddr_a_i : read port A index (rs1)   -> rdata_a_o (combinational)
//   raddr_b_i : read port B index (rs2)   -> rdata_b_o (combinational)
//
// Timing:
//   Reads are combinational: change the address, the data appears within the
//   same cycle. Writes are synchronous. If you read and write the same
//   register in the same cycle, the read returns the OLD value (the new one
//   is visible after the clock edge). The single-cycle core never hits this
//   case; a pipelined core will need forwarding — noted for later.
//
// Note on reset:
//   The register array is intentionally not reset. RISC-V does not define
//   register values at reset (except x0) and real cores don't reset the file;
//   software initializes what it needs. This also maps better to FPGA BRAM.
// ============================================================================

module regfile (
    input  logic        clk_i,
    // write port
    input  logic        we_i,
    input  logic [4:0]  waddr_i,
    input  logic [31:0] wdata_i,
    // read port A (rs1)
    input  logic [4:0]  raddr_a_i,
    output logic [31:0] rdata_a_o,
    // read port B (rs2)
    input  logic [4:0]  raddr_b_i,
    output logic [31:0] rdata_b_o
);

  // 31 real registers; x0 is not stored, it is synthesized as constant 0
  logic [31:0] regs[1:31];

  // ---- synchronous write (x0 writes discarded) -----------------------------
  always_ff @(posedge clk_i) begin
    if (we_i && (waddr_i != 5'd0)) begin
      regs[waddr_i] <= wdata_i;
    end
  end

  // ---- combinational reads (x0 reads as zero) -------------------------------
  assign rdata_a_o = (raddr_a_i == 5'd0) ? 32'd0 : regs[raddr_a_i];
  assign rdata_b_o = (raddr_b_i == 5'd0) ? 32'd0 : regs[raddr_b_i];

endmodule

tb/unit/tb_regfile.sv
// ============================================================================
// tb_regfile.sv — self-checking testbench for the register file
// ----------------------------------------------------------------------------
// Tests:
//   1. x0 always reads zero, even after a write attempt to x0
//   2. Write then read back, all 31 real registers
//   3. Dual read ports return independent, correct data
//   4. we_i = 0 blocks writes
//   5. Read-during-write returns OLD value (documented behavior)
//   6. Random write/read soak test against a software model
// ============================================================================

`timescale 1ns / 1ps

module tb_regfile;

  logic        clk;
  logic        we;
  logic [4:0]  waddr, raddr_a, raddr_b;
  logic [31:0] wdata, rdata_a, rdata_b;

  int errors = 0;
  int checks = 0;

  // software reference model
  logic [31:0] model[0:31];

  regfile dut (
      .clk_i    (clk),
      .we_i     (we),
      .waddr_i  (waddr),
      .wdata_i  (wdata),
      .raddr_a_i(raddr_a),
      .rdata_a_o(rdata_a),
      .raddr_b_i(raddr_b),
      .rdata_b_o(rdata_b)
  );

  initial clk = 0;
  always #5 clk = ~clk;

  task automatic check(input [31:0] got, input [31:0] expected, input string what);
    checks++;
    if (got !== expected) begin
      errors++;
      $display("FAIL: %s | expected 0x%08h, got 0x%08h (t=%0t)",
               what, expected, got, $time);
    end
  endtask

  // write one register through the DUT and mirror it in the model
  task automatic write_reg(input [4:0] a, input [31:0] d);
    @(negedge clk);
    we    = 1;
    waddr = a;
    wdata = d;
    @(posedge clk);
    #1 we = 0;
    if (a != 0) model[a] = d;
  endtask

  initial begin
    $dumpfile("tb_regfile.vcd");
    $dumpvars(0, tb_regfile);
    we = 0; waddr = 0; wdata = 0; raddr_a = 0; raddr_b = 0;
    for (int i = 0; i < 32; i++) model[i] = 0;

    // ---- Test 1: x0 behavior --------------------------------------------
    write_reg(5'd0, 32'hFFFF_FFFF);   // attempt write to x0
    raddr_a = 0; raddr_b = 0;
    #1;
    check(rdata_a, 32'd0, "x0 reads zero on port A");
    check(rdata_b, 32'd0, "x0 reads zero on port B");

    // ---- Test 2: write/readback all registers ---------------------------
    for (int i = 1; i < 32; i++) write_reg(i[4:0], 32'hA000_0000 + i);
    for (int i = 1; i < 32; i++) begin
      raddr_a = i[4:0];
      #1 check(rdata_a, 32'hA000_0000 + i, $sformatf("readback x%0d", i));
    end

    // ---- Test 3: independent dual read ----------------------------------
    raddr_a = 5'd3; raddr_b = 5'd17;
    #1;
    check(rdata_a, 32'hA000_0003, "dual read port A (x3)");
    check(rdata_b, 32'hA000_0011, "dual read port B (x17)");

    // ---- Test 4: we=0 blocks writes --------------------------------------
    @(negedge clk);
    we = 0; waddr = 5'd5; wdata = 32'h1234_5678;
    @(posedge clk);
    #1 raddr_a = 5'd5;
    #1 check(rdata_a, 32'hA000_0005, "we=0 blocks write to x5");

    // ---- Test 5: read-during-write returns old value ---------------------
    @(negedge clk);
    we = 1; waddr = 5'd9; wdata = 32'hCAFE_F00D; raddr_a = 5'd9;
    #1 check(rdata_a, 32'hA000_0009, "read-during-write sees OLD value");
    @(posedge clk);
    #1 we = 0;
    model[9] = 32'hCAFE_F00D;
    check(rdata_a, 32'hCAFE_F00D, "new value visible after edge");

    // ---- Test 6: random soak vs model -------------------------------------
    for (int n = 0; n < 200; n++) begin
      write_reg($random, $random);
      raddr_a = $random;
      raddr_b = $random;
      #1;
      check(rdata_a, (raddr_a == 0) ? 0 : model[raddr_a], "random port A");
      check(rdata_b, (raddr_b == 0) ? 0 : model[raddr_b], "random port B");
    end

    // ---- Summary -----------------------------------------------------------
    if (errors == 0) $display("RESULT: PASS (%0d checks)", checks);
    else             $display("RESULT: FAIL (%0d/%0d checks failed)", errors, checks);
    $finish;
  end

endmodule

sim/icarus/build/tb_regfile.vcd
$date
	Sun Jul  5 00:07:39 2026
$end
$version
	Icarus Verilog
$end
$timescale
	1ps
$end
$scope module tb_regfile $end
$var wire 32 ! rdata_b [31:0] $end
$var wire 32 " rdata_a [31:0] $end
$var reg 1 # clk $end
$var reg 5 $ raddr_a [4:0] $end
$var reg 5 % raddr_b [4:0] $end
$var reg 5 & waddr [4:0] $end
$var reg 32 ' wdata [31:0] $end
$var reg 1 ( we $end
$var integer 32 ) checks [31:0] $end
$var integer 32 * errors [31:0] $end
$scope module dut $end
$var wire 1 # clk_i $end
$var wire 5 + raddr_a_i [4:0] $end
$var wire 5 , raddr_b_i [4:0] $end
$var wire 5 - waddr_i [4:0] $end
$var wire 32 . wdata_i [31:0] $end
$var wire 1 ( we_i $end
$var wire 32 / rdata_b_o [31:0] $end
$var wire 32 0 rdata_a_o [31:0] $end
$upscope $end
$scope begin $ivl_for_loop0 $end
$var integer 32 1 i [31:0] $end
$upscope $end
$scope begin $ivl_for_loop1 $end
$var integer 32 2 i [31:0] $end
$upscope $end
$scope begin $ivl_for_loop2 $end
$var integer 32 3 i [31:0] $end
$upscope $end
$scope begin $ivl_for_loop3 $end
$var integer 32 4 n [31:0] $end
$upscope $end
$scope task check $end
$upscope $end
$scope task write_reg $end
$upscope $end
$upscope $end
$enddefinitions $end
#0
$dumpvars
b0 4
b0 3
b0 2
b100000 1
b0 0
b0 /
b0 .
b0 -
b0 ,
b0 +
b0 *
b0 )
0(
b0 '
b0 &
b0 %
b0 $
0#
b0 "
b0 !
$end
#5000
1#
#10000
b11111111111111111111111111111111 '
b11111111111111111111111111111111 .
1(
0#
#15000
1#
#16000
0(
#17000
b1 2
b10 )
#20000
b10100000000000000000000000000001 '
b10100000000000000000000000000001 .
b1 &
b1 -
1(
0#
#25000
1#
#26000
b10 2
0(
#30000
b10100000000000000000000000000010 '
b10100000000000000000000000000010 .
b10 &
b10 -
1(
0#
#35000
1#
#36000
b11 2
0(
#40000
b10100000000000000000000000000011 '
b10100000000000000000000000000011 .
b11 &
b11 -
1(
0#
#45000
1#
#46000
b100 2
0(
#50000
b10100000000000000000000000000100 '
b10100000000000000000000000000100 .
b100 &
b100 -
1(
0#
#55000
1#
#56000
b101 2
0(
#60000
b10100000000000000000000000000101 '
b10100000000000000000000000000101 .
b101 &
b101 -
1(
0#
#65000
1#
#66000
b110 2
0(
#70000
b10100000000000000000000000000110 '
b10100000000000000000000000000110 .
b110 &
b110 -
1(
0#
#75000
1#
#76000
b111 2
0(
#80000
b10100000000000000000000000000111 '
b10100000000000000000000000000111 .
b111 &
b111 -
1(
0#
#85000
1#
#86000
b1000 2
0(
#90000
b10100000000000000000000000001000 '
b10100000000000000000000000001000 .
b1000 &
b1000 -
1(
0#
#95000
1#
#96000
b1001 2
0(
#100000
b10100000000000000000000000001001 '
b10100000000000000000000000001001 .
b1001 &
b1001 -
1(
0#
#105000
1#
#106000
b1010 2
0(
#110000
b10100000000000000000000000001010 '
b10100000000000000000000000001010 .
b1010 &
b1010 -
1(
0#
#115000
1#
#116000
b1011 2
0(
#120000
b10100000000000000000000000001011 '
b10100000000000000000000000001011 .
b1011 &
b1011 -
1(
0#
#125000
1#
#126000
b1100 2
0(
#130000
b10100000000000000000000000001100 '
b10100000000000000000000000001100 .
b1100 &
b1100 -
1(
0#
#135000
1#
#136000
b1101 2
0(
#140000
b10100000000000000000000000001101 '
b10100000000000000000000000001101 .
b1101 &
b1101 -
1(
0#
#145000
1#
#146000
b1110 2
0(
#150000
b10100000000000000000000000001110 '
b10100000000000000000000000001110 .
b1110 &
b1110 -
1(
0#
#155000
1#
#156000
b1111 2
0(
#160000
b10100000000000000000000000001111 '
b10100000000000000000000000001111 .
b1111 &
b1111 -
1(
0#
#165000
1#
#166000
b10000 2
0(
#170000
b10100000000000000000000000010000 '
b10100000000000000000000000010000 .
b10000 &
b10000 -
1(
0#
#175000
1#
#176000
b10001 2
0(
#180000
b10100000000000000000000000010001 '
b10100000000000000000000000010001 .
b10001 &
b10001 -
1(
0#
#185000
1#
#186000
b10010 2
0(
#190000
b10100000000000000000000000010010 '
b10100000000000000000000000010010 .
b10010 &
b10010 -
1(
0#
#195000
1#
#196000
b10011 2
0(
#200000
b10100000000000000000000000010011 '
b10100000000000000000000000010011 .
b10011 &
b10011 -
1(
0#
#205000
1#
#206000
b10100 2
0(
#210000
b10100000000000000000000000010100 '
b10100000000000000000000000010100 .
b10100 &
b10100 -
1(
0#
#215000
1#
#216000
b10101 2
0(
#220000
b10100000000000000000000000010101 '
b10100000000000000000000000010101 .
b10101 &
b10101 -
1(
0#
#225000
1#
#226000
b10110 2
0(
#230000
b10100000000000000000000000010110 '
b10100000000000000000000000010110 .
b10110 &
b10110 -
1(
0#
#235000
1#
#236000
b10111 2
0(
#240000
b10100000000000000000000000010111 '
b10100000000000000000000000010111 .
b10111 &
b10111 -
1(
0#
#245000
1#
#246000
b11000 2
0(
#250000
b10100000000000000000000000011000 '
b10100000000000000000000000011000 .
b11000 &
b11000 -
1(
0#
#255000
1#
#256000
b11001 2
0(
#260000
b10100000000000000000000000011001 '
b10100000000000000000000000011001 .
b11001 &
b11001 -
1(
0#
#265000
1#
#266000
b11010 2
0(
#270000
b10100000000000000000000000011010 '
b10100000000000000000000000011010 .
b11010 &
b11010 -
1(
0#
#275000
1#
#276000
b11011 2
0(
#280000
b10100000000000000000000000011011 '
b10100000000000000000000000011011 .
b11011 &
b11011 -
1(
0#
#285000
1#
#286000
b11100 2
0(
#290000
b10100000000000000000000000011100 '
b10100000000000000000000000011100 .
b11100 &
b11100 -
1(
0#
#295000
1#
#296000
b11101 2
0(
#300000
b10100000000000000000000000011101 '
b10100000000000000000000000011101 .
b11101 &
b11101 -
1(
0#
#305000
1#
#306000
b11110 2
0(
#310000
b10100000000000000000000000011110 '
b10100000000000000000000000011110 .
b11110 &
b11110 -
1(
0#
#315000
1#
#316000
b11111 2
0(
#320000
b10100000000000000000000000011111 '
b10100000000000000000000000011111 .
b11111 &
b11111 -
1(
0#
#325000
1#
#326000
b10100000000000000000000000000001 "
b10100000000000000000000000000001 0
b1 $
b1 +
b1 3
b100000 2
0(
#327000
b10100000000000000000000000000010 "
b10100000000000000000000000000010 0
b10 $
b10 +
b10 3
b11 )
#328000
b10100000000000000000000000000011 "
b10100000000000000000000000000011 0
b11 $
b11 +
b11 3
b100 )
#329000
b10100000000000000000000000000100 "
b10100000000000000000000000000100 0
b100 $
b100 +
b100 3
b101 )
#330000
b10100000000000000000000000000101 "
b10100000000000000000000000000101 0
b101 $
b101 +
b101 3
b110 )
0#
#331000
b10100000000000000000000000000110 "
b10100000000000000000000000000110 0
b110 $
b110 +
b110 3
b111 )
#332000
b10100000000000000000000000000111 "
b10100000000000000000000000000111 0
b111 $
b111 +
b111 3
b1000 )
#333000
b10100000000000000000000000001000 "
b10100000000000000000000000001000 0
b1000 $
b1000 +
b1000 3
b1001 )
#334000
b10100000000000000000000000001001 "
b10100000000000000000000000001001 0
b1001 $
b1001 +
b1001 3
b1010 )
#335000
b10100000000000000000000000001010 "
b10100000000000000000000000001010 0
b1010 $
b1010 +
b1010 3
b1011 )
1#
#336000
b10100000000000000000000000001011 "
b10100000000000000000000000001011 0
b1011 $
b1011 +
b1011 3
b1100 )
#337000
b10100000000000000000000000001100 "
b10100000000000000000000000001100 0
b1100 $
b1100 +
b1100 3
b1101 )
#338000
b10100000000000000000000000001101 "
b10100000000000000000000000001101 0
b1101 $
b1101 +
b1101 3
b1110 )
#339000
b10100000000000000000000000001110 "
b10100000000000000000000000001110 0
b1110 $
b1110 +
b1110 3
b1111 )
#340000
b10100000000000000000000000001111 "
b10100000000000000000000000001111 0
b1111 $
b1111 +
b1111 3
b10000 )
0#
#341000
b10100000000000000000000000010000 "
b10100000000000000000000000010000 0
b10000 $
b10000 +
b10000 3
b10001 )
#342000
b10100000000000000000000000010001 "
b10100000000000000000000000010001 0
b10001 $
b10001 +
b10001 3
b10010 )
#343000
b10100000000000000000000000010010 "
b10100000000000000000000000010010 0
b10010 $
b10010 +
b10010 3
b10011 )
#344000
b10100000000000000000000000010011 "
b10100000000000000000000000010011 0
b10011 $
b10011 +
b10011 3
b10100 )
#345000
b10100000000000000000000000010100 "
b10100000000000000000000000010100 0
b10100 $
b10100 +
b10100 3
b10101 )
1#
#346000
b10100000000000000000000000010101 "
b10100000000000000000000000010101 0
b10101 $
b10101 +
b10101 3
b10110 )
#347000
b10100000000000000000000000010110 "
b10100000000000000000000000010110 0
b10110 $
b10110 +
b10110 3
b10111 )
#348000
b10100000000000000000000000010111 "
b10100000000000000000000000010111 0
b10111 $
b10111 +
b10111 3
b11000 )
#349000
b10100000000000000000000000011000 "
b10100000000000000000000000011000 0
b11000 $
b11000 +
b11000 3
b11001 )
#350000
b10100000000000000000000000011001 "
b10100000000000000000000000011001 0
b11001 $
b11001 +
b11001 3
b11010 )
0#
#351000
b10100000000000000000000000011010 "
b10100000000000000000000000011010 0
b11010 $
b11010 +
b11010 3
b11011 )
#352000
b10100000000000000000000000011011 "
b10100000000000000000000000011011 0
b11011 $
b11011 +
b11011 3
b11100 )
#353000
b10100000000000000000000000011100 "
b10100000000000000000000000011100 0
b11100 $
b11100 +
b11100 3
b11101 )
#354000
b10100000000000000000000000011101 "
b10100000000000000000000000011101 0
b11101 $
b11101 +
b11101 3
b11110 )
#355000
b10100000000000000000000000011110 "
b10100000000000000000000000011110 0
b11110 $
b11110 +
b11110 3
b11111 )
1#
#356000
b10100000000000000000000000011111 "
b10100000000000000000000000011111 0
b11111 $
b11111 +
b11111 3
b100000 )
#357000
b10100000000000000000000000010001 !
b10100000000000000000000000010001 /
b10100000000000000000000000000011 "
b10100000000000000000000000000011 0
b10001 %
b10001 ,
b11 $
b11 +
b100000 3
b100001 )
#358000
b100011 )
#360000
b10010001101000101011001111000 '
b10010001101000101011001111000 .
b101 &
b101 -
0#
#365000
1#
#366000
b10100000000000000000000000000101 "
b10100000000000000000000000000101 0
b101 $
b101 +
#367000
b100100 )
#370000
b10100000000000000000000000001001 "
b10100000000000000000000000001001 0
b1001 $
b1001 +
b11001010111111101111000000001101 '
b11001010111111101111000000001101 .
b1001 &
b1001 -
1(
0#
#371000
b100101 )
#375000
b11001010111111101111000000001101 "
b11001010111111101111000000001101 0
1#
#376000
b100110 )
0(
#380000
b11000000100010010101111010000001 '
b11000000100010010101111010000001 .
b100 &
b100 -
1(
0#
#385000
1#
#386000
b10100000000000000000000000000011 !
b10100000000000000000000000000011 /
b11 %
b11 ,
0(
#387000
b1 4
b101000 )
#390000
b1000110110111111001100110001101 '
b1000110110111111001100110001101 .
b1101 &
b1101 -
1(
0#
#395000
1#
#396000
b10100000000000000000000000010010 !
b10100000000000000000000000010010 /
b10100000000000000000000000000101 "
b10100000000000000000000000000101 0
b10010 %
b10010 ,
b101 $
b101 +
0(
#397000
b10 4
b101010 )
#400000
b110110101111100110100001101 '
b110110101111100110100001101 .
b1 &
b1 -
1(
0#
#405000
1#
#406000
b10100000000000000000000000011101 !
b10100000000000000000000000011101 /
b10100000000000000000000000010110 "
b10100000000000000000000000010110 0
b11101 %
b11101 ,
b10110 $
b10110 +
0(
#407000
b11 4
b101100 )
#410000
b1000110001011011111011110001100 '
b1000110001011011111011110001100 .
b1101 &
b1101 -
1(
0#
#415000
1#
#416000
b10100000000000000000000000000110 !
b10100000000000000000000000000110 /
b10100000000000000000000000011001 "
b10100000000000000000000000011001 0
b110 %
b110 ,
b11001 $
b11001 +
0(
#417000
b100 4
b101110 )
#420000
b11010101000100111101001010101010 '
b11010101000100111101001010101010 .
b101 &
b101 -
1(
0#
#425000
1#
#426000
b10100000000000000000000000010111 !
b10100000000000000000000000010111 /
b11010101000100111101001010101010 "
b11010101000100111101001010101010 0
b10111 %
b10111 ,
b101 $
b101 +
0(
#427000
b101 4
b110000 )
#430000
b1000111111011001101101110001111 '
b1000111111011001101101110001111 .
b10010 &
b10010 -
1(
0#
#435000
1#
#436000
b10100000000000000000000000001110 !
b10100000000000000000000000001110 /
b1000111111011001101101110001111 "
b1000111111011001101101110001111 0
b1110 %
b1110 ,
b10010 $
b10010 +
0(
#437000
b110 4
b110010 )
#440000
b11100010110010100100111011000101 '
b11100010110010100100111011000101 .
b1000 &
b1000 -
1(
0#
#445000
1#
#446000
b10100000000000000000000000011101 !
b10100000000000000000000000011101 /
b10100000000000000000000000011100 "
b10100000000000000000000000011100 0
b11101 %
b11101 ,
b11100 $
b11100 +
0(
#447000
b111 4
b110100 )
#450000
b10110010101001110010011001100101 '
b10110010101001110010011001100101 .
b1101 &
b1101 -
1(
0#
#455000
1#
#456000
b10100000000000000000000000001010 !
b10100000000000000000000000001010 /
b10100000000000000000000000000011 "
b10100000000000000000000000000011 0
b1010 %
b1010 ,
b11 $
b11 +
0(
#457000
b1000 4
b110110 )
#460000
b10000011001000010000100100000 '
b10000011001000010000100100000 .
b0 &
b0 -
1(
0#
#465000
1#
#466000
b10100000000000000000000000011101 !
b10100000000000000000000000011101 /
b10100000000000000000000000001010 "
b10100000000000000000000000001010 0
b11101 %
b11101 ,
b1010 $
b1010 +
0(
#467000
b1001 4
b111000 )
#470000
b10001001100000111011100000010011 '
b10001001100000111011100000010011 .
b10110 &
b10110 -
1(
0#
#475000
1#
#476000
b10100000000000000000000000010011 !
b10100000000000000000000000010011 /
b10110010101001110010011001100101 "
b10110010101001110010011001100101 0
b10011 %
b10011 ,
b1101 $
b1101 +
0(
#477000
b1010 4
b111010 )
#480000
b11101010101001100010101011010101 '
b11101010101001100010101011010101 .
b1011 &
b1011 -
1(
0#
#485000
1#
#486000
b10100000000000000000000000001110 !
b10100000000000000000000000001110 /
b10100000000000000000000000000010 "
b10100000000000000000000000000010 0
b1110 %
b1110 ,
b10 $
b10 +
0(
#487000
b1011 4
b111100 )
#490000
b11100111110001010111001011001111 '
b11100111110001010111001011001111 .
b11101 &
b11101 -
1(
0#
#495000
1#
#496000
b10100000000000000000000000001010 !
b10100000000000000000000000001010 /
b10100000000000000000000000000011 "
b10100000000000000000000000000011 0
b1010 %
b1010 ,
b11 $
b11 +
0(
#497000
b1100 4
b111110 )
#500000
b10011110001100010100110000111100 '
b10011110001100010100110000111100 .
b1010 &
b1010 -
1(
0#
#505000
b10011110001100010100110000111100 !
b10011110001100010100110000111100 /
1#
#506000
b1000111111011001101101110001111 "
b1000111111011001101101110001111 0
b10010 $
b10010 +
0(
#507000
b1101 4
b1000000 )
#510000
b11101100010010110011010011011000 '
b11101100010010110011010011011000 .
b1 &
b1 -
1(
0#
#515000
1#
#516000
b11001010111111101111000000001101 !
b11001010111111101111000000001101 /
b10100000000000000000000000011000 "
b10100000000000000000000000011000 0
b1001 %
b1001 ,
b11000 $
b11000 +
0(
#517000
b1110 4
b1000010 )
#520000
b1011011000000100110010110110110 '
b1011011000000100110010110110110 .
b1011 &
b1011 -
1(
0#
#525000
1#
#526000
b10100000000000000000000000001110 !
b10100000000000000000000000001110 /
b10100000000000000000000000000110 "
b10100000000000000000000000000110 0
b1110 %
b1110 ,
b110 $
b110 +
0(
#527000
b1111 4
b1000100 )
#530000
b10101000011111101110100101010 '
b10101000011111101110100101010 .
b11100 &
b11100 -
1(
0#
#535000
1#
#536000
b10100000000000000000000000010001 !
b10100000000000000000000000010001 /
b1011011000000100110010110110110 "
b1011011000000100110010110110110 0
b10001 %
b10001 ,
b1011 $
b1011 +
0(
#537000
b10000 4
b1000110 )
#540000
b100111111100100101010101001111 '
b100111111100100101010101001111 .
b101 &
b101 -
1(
0#
#545000
1#
#546000
b10100000000000000000000000011010 !
b10100000000000000000000000011010 /
b10100000000000000000000000011011 "
b10100000000000000000000000011011 0
b11010 %
b11010 ,
b11011 $
b11011 +
0(
#547000
b10001 4
b1001000 )
#550000
b1010101010100100101100010101 '
b1010101010100100101100010101 .
b11110 &
b11110 -
1(
0#
#555000
1#
#556000
b10100000000000000000000000011001 !
b10100000000000000000000000011001 /
b10100000000000000000000000010001 "
b10100000000000000000000000010001 0
b11001 %
b11001 ,
b10001 $
b10001 +
0(
#557000
b10010 4
b1001010 )
#560000
b100110001101011111101101001100 '
b100110001101011111101101001100 .
b10 &
b10 -
1(
0#
#565000
1#
#566000
b10100000000000000000000000001111 !
b10100000000000000000000000001111 /
b10100000000000000000000000011111 "
b10100000000000000000000000011111 0
b1111 %
b1111 ,
b11111 $
b11111 +
0(
#567000
b10011 4
b1001100 )
#570000
b11011011110011010110000010110111 '
b11011011110011010110000010110111 .
b11000 &
b11000 -
1(
0#
#575000
1#
#576000
b10101000011111101110100101010 !
b10101000011111101110100101010 /
b11100 %
b11100 ,
0(
#577000
b10100 4
b1001110 )
#580000
b1000100110111100011011110001001 '
b1000100110111100011011110001001 .
b11011 &
b11011 -
1(
0#
#585000
1#
#586000
b10100000000000000000000000010000 !
b10100000000000000000000000010000 /
b11001010111111101111000000001101 "
b11001010111111101111000000001101 0
b10000 %
b10000 ,
b1001 $
b1001 +
0(
#587000
b10101 4
b1010000 )
#590000
b10101000110001111111110001010001 '
b10101000110001111111110001010001 .
b10111 &
b10111 -
1(
0#
#595000
1#
#596000
b10100000000000000000000000001100 !
b10100000000000000000000000001100 /
b10001001100000111011100000010011 "
b10001001100000111011100000010011 0
b1100 %
b1100 ,
b10110 $
b10110 +
0(
#597000
b10110 4
b1010010 )
#600000
b1100100010101111110110111001000 '
b1100100010101111110110111001000 .
b10 &
b10 -
1(
0#
#605000
1#
#606000
b11100111110001010111001011001111 !
b11100111110001010111001011001111 /
b10101000110001111111110001010001 "
b10101000110001111111110001010001 0
b11101 %
b11101 ,
b10111 $
b10111 +
0(
#607000
b10111 4
b1010100 )
#610000
b10111111000001010000000001111110 '
b10111111000001010000000001111110 .
b10010 &
b10010 -
1(
0#
#615000
1#
#616000
b10100000000000000000000000011001 !
b10100000000000000000000000011001 /
b10110010101001110010011001100101 "
b10110010101001110010011001100101 0
b11001 %
b11001 ,
b1101 $
b1101 +
0(
#617000
b11000 4
b1010110 )
#620000
b11101001111010111111011011010011 '
b11101001111010111111011011010011 .
b11111 &
b11111 -
1(
0#
#625000
1#
#626000
b11011011110011010110000010110111 !
b11011011110011010110000010110111 /
b100111111100100101010101001111 "
b100111111100100101010101001111 0
b11000 %
b11000 ,
b101 $
b101 +
0(
#627000
b11001 4
b1011000 )
#630000
b100100100010110100101101001001 '
b100100100010110100101101001001 .
b11011 &
b11011 -
1(
0#
#635000
1#
#636000
b10011110001100010100110000111100 !
b10011110001100010100110000111100 /
b11101001111010111111011011010011 "
b11101001111010111111011011010011 0
b1010 %
b1010 ,
b11111 $
b11111 +
0(
#637000
b11010 4
b1011010 )
#640000
b11000011001111110011100010000110 '
b11000011001111110011100010000110 .
b11000 &
b11000 -
1(
0#
#645000
1#
#646000
b10101000011111101110100101010 !
b10101000011111101110100101010 /
b10100000000000000000000000001110 "
b10100000000000000000000000001110 0
b11100 %
b11100 ,
b1110 $
b1110 +
0(
#647000
b11011 4
b1011100 )
#650000
b10010011011111011011110000100110 '
b10010011011111011011110000100110 .
b11010 &
b11010 -
1(
0#
#655000
1#
#656000
b10100000000000000000000000000011 !
b10100000000000000000000000000011 /
b10100000000000000000000000010011 "
b10100000000000000000000000010011 0
b11 %
b11 ,
b10011 $
b10011 +
0(
#657000
b11100 4
b1011110 )
#660000
b11011001110100101001001010110011 '
b11011001110100101001001010110011 .
b1111 &
b1111 -
1(
0#
#665000
1#
#666000
b11000000100010010101111010000001 !
b11000000100010010101111010000001 /
b11101001111010111111011011010011 "
b11101001111010111111011011010011 0
b100 %
b100 ,
b11111 $
b11111 +
0(
#667000
b11101 4
b1100000 )
#670000
b11100101100110110011011011001011 '
b11100101100110110011011011001011 .
b10111 &
b10111 -
1(
0#
#675000
1#
#676000
b10010011011111011011110000100110 !
b10010011011111011011110000100110 /
b10100000000000000000000000000110 "
b10100000000000000000000000000110 0
b11010 %
b11010 ,
b110 $
b110 +
0(
#677000
b11110 4
b1100010 )
#680000
b11110110100000101110001011101101 '
b11110110100000101110001011101101 .
b1001 &
b1001 -
1(
0#
#685000
1#
#686000
b100111111100100101010101001111 !
b100111111100100101010101001111 /
b10010011011111011011110000100110 "
b10010011011111011011110000100110 0
b101 %
b101 ,
b11010 $
b11010 +
0(
#687000
b11111 4
b1100100 )
#690000
b11101111101111101001010011011111 '
b11101111101111101001010011011111 .
b10101 &
b10101 -
1(
0#
#695000
1#
#696000
b11000000100010010101111010000001 !
b11000000100010010101111010000001 /
b10100000000000000000000000011001 "
b10100000000000000000000000011001 0
b100 %
b100 ,
b11001 $
b11001 +
0(
#697000
b100000 4
b1100110 )
#700000
b10101000010010000101100101010 '
b10101000010010000101100101010 .
b10000 &
b10000 -
1(
0#
#705000
1#
#706000
b10100000000000000000000000001110 !
b10100000000000000000000000001110 /
b1011011000000100110010110110110 "
b1011011000000100110010110110110 0
b1110 %
b1110 ,
b1011 $
b1011 +
0(
#707000
b100001 4
b1101000 )
#710000
b11001101010111101011110010011010 '
b11001101010111101011110010011010 .
b11100 &
b11100 -
1(
0#
#715000
1#
#716000
b10100000000000000000000000000011 !
b10100000000000000000000000000011 /
b11100111110001010111001011001111 "
b11100111110001010111001011001111 0
b11 %
b11 ,
b11101 $
b11101 +
0(
#717000
b100010 4
b1101010 )
#720000
b100111011110011110100101001110 '
b100111011110011110100101001110 .
b10110 &
b10110 -
1(
0#
#725000
1#
#726000
b10011110001100010100110000111100 !
b10011110001100010100110000111100 /
b10100000000000000000000000000111 "
b10100000000000000000000000000111 0
b1010 %
b1010 ,
b111 $
b111 +
0(
#727000
b100011 4
b1101100 )
#730000
b10011100000011101000101000111000 '
b10011100000011101000101000111000 .
1(
0#
#735000
1#
#736000
b11000011001111110011100010000110 !
b11000011001111110011100010000110 /
b10100000000000000000000000011001 "
b10100000000000000000000000011001 0
b11000 %
b11000 ,
b11001 $
b11001 +
0(
#737000
b100100 4
b1101110 )
#740000
b1001001110001100101110110010011 '
b1001001110001100101110110010011 .
b10100 &
b10100 -
1(
0#
#745000
1#
#746000
b10100000000000000000000000011001 !
b10100000000000000000000000011001 /
b11000000100010010101111010000001 "
b11000000100010010101111010000001 0
b11001 %
b11001 ,
b100 $
b100 +
0(
#747000
b100101 4
b1110000 )
#750000
b10100110111111001101111001001101 '
b10100110111111001101111001001101 .
b11011 &
b11011 -
1(
0#
#755000
1#
#756000
b10110010101001110010011001100101 !
b10110010101001110010011001100101 /
b10100000000000000000000000011001 "
b10100000000000000000000000011001 0
b1101 %
b1101 ,
b11001 $
b11001 +
0(
#757000
b100110 4
b1110010 )
#760000
b1100101001110110100100111001010 '
b1100101001110110100100111001010 .
b10110 &
b10110 -
1(
0#
#765000
1#
#766000
b11101111101111101001010011011111 !
b11101111101111101001010011011111 /
b1100101001110110100100111001010 "
b1100101001110110100100111001010 0
b10101 %
b10101 ,
b10110 $
b10110 +
0(
#767000
b100111 4
b1110100 )
#770000
b10011101001001101100000100 '
b10011101001001101100000100 .
b110 &
b110 -
1(
0#
#775000
1#
#776000
b11110110100000101110001011101101 !
b11110110100000101110001011101101 /
b11100101100110110011011011001011 "
b11100101100110110011011011001011 0
b1001 %
b1001 ,
b10111 $
b10111 +
0(
#777000
b101000 4
b1110110 )
#780000
b1000100000000011000110110001000 '
b1000100000000011000110110001000 .
b10100 &
b10100 -
1(
0#
#785000
1#
#786000
b10110010101001110010011001100101 !
b10110010101001110010011001100101 /
b11100010110010100100111011000101 "
b11100010110010100100111011000101 0
b1101 %
b1101 ,
b1000 $
b1000 +
0(
#787000
b101001 4
b1111000 )
#790000
b10010111010111001001110000101110 '
b10010111010111001001110000101110 .
b111 &
b111 -
1(
0#
#795000
1#
#796000
b11001101010111101011110010011010 !
b11001101010111101011110010011010 /
b11100 %
b11100 ,
0(
#797000
b101010 4
b1111010 )
#800000
b10100100111100000011100101001 '
b10100100111100000011100101001 .
b11101 &
b11101 -
1(
0#
#805000
1#
